wagtailorderable/__init__.py
wagtailorderable/models.py
wagtailorderable/signals.py
wagtailorderable/__pycache__/__init__.cpython-310.pyc
wagtailorderable/modeladmin/__init__.py
wagtailorderable/modeladmin/mixins.py
wagtailorderable/static/wagtailorderable/modeladmin/css/orderablemixin.css
wagtailorderable/static/wagtailorderable/modeladmin/js/orderablemixin.js
wagtail_orderable-1.2.0.dist-info/LICENSE.txt
wagtail_orderable-1.2.0.dist-info/METADATA
wagtail_orderable-1.2.0.dist-info/WHEEL
wagtail_orderable-1.2.0.dist-info/top_level.txt
wagtail_orderable-1.2.0.dist-info/RECORD
